django_request_vars-1.0.1.dist-info/METADATA
django_request_vars-1.0.1.dist-info/RECORD
django_request_vars-1.0.1.dist-info/WHEEL
django_request_vars-1.0.1.dist-info/top_level.txt
request_vars/__init__.py
request_vars/apps.py
request_vars/conf.py
request_vars/decorators.py
request_vars/middleware.py
request_vars/utils.py
request_vars/templatetags/__init__.py
request_vars/templatetags/request_vars.py
