Metadata-Version: 1.1
Name: django-request-vars
Version: 1.0.1
Summary: Stores current request, user and your defined data in thread local variable.
Home-page: https://github.com/kindlycat/django-request-vars/
Author: Grigory Mishchenko
Author-email: grishkokot@gmail.com
License: UNKNOWN
Keywords: django,thread,variable,request,user,cache,middleware
Platform: UNKNOWN
Classifier: Development Status :: 4 - Beta
Classifier: Programming Language :: Python :: 2.7
Classifier: Programming Language :: Python :: 3.5
Classifier: Programming Language :: Python :: 3.6
Classifier: Framework :: Django :: 1.11
Classifier: Framework :: Django :: 2.0
Classifier: License :: OSI Approved :: BSD License
